swh/export/__init__.py
swh/export/athena.py
swh/export/cli.py
swh/export/exporter.py
swh/export/fullnames.py
swh/export/journalprocessor.py
swh/export/luigi.py
swh/export/py.typed
swh/export/relational.py
swh/export/utils.py
swh/export/exporters/__init__.py
swh/export/exporters/edges.py
swh/export/exporters/orc.py
swh/export/test/test_edges.py
swh/export/test/test_journal_processor.py
swh/export/test/test_orc.py
swh/export/test/test_utils.py
swh_export-1.11.6.dist-info/licenses/AUTHORS
swh_export-1.11.6.dist-info/licenses/LICENSE
swh_export-1.11.6.dist-info/METADATA
swh_export-1.11.6.dist-info/WHEEL
swh_export-1.11.6.dist-info/entry_points.txt
swh_export-1.11.6.dist-info/top_level.txt
swh_export-1.11.6.dist-info/RECORD
