Metadata-Version: 2.4
Name: swh.export
Version: 1.11.6
Summary: Software Heritage dataset tools
Author-email: Software Heritage developers <swh-devel@inria.fr>
Project-URL: Homepage, https://gitlab.softwareheritage.org/swh/devel/swh-export
Project-URL: Bug Reports, https://gitlab.softwareheritage.org/swh/devel/swh-export/-/issues
Project-URL: Funding, https://www.softwareheritage.org/donate
Project-URL: Documentation, https://docs.softwareheritage.org/devel/swh-export/
Project-URL: Source, https://gitlab.softwareheritage.org/swh/devel/swh-export.git
Classifier: Programming Language :: Python :: 3
Classifier: Intended Audience :: Developers
Classifier: License :: OSI Approved :: GNU General Public License v3 (GPLv3)
Classifier: Operating System :: OS Independent
Classifier: Development Status :: 3 - Alpha
Requires-Python: >=3.9
License-File: LICENSE
License-File: AUTHORS
Requires-Dist: boto3
Requires-Dist: click
Requires-Dist: luigi!=3.5.2,!=3.7.0,!=3.7.1
Requires-Dist: tqdm
Requires-Dist: pyorc; python_version >= "3.8"
Requires-Dist: pyorc<0.9; python_version < "3.8"
Requires-Dist: plyvel
Requires-Dist: types-requests; python_version >= "3.10"
Requires-Dist: types-requests<2.31.0.7; python_version < "3.10"
Requires-Dist: swh.core[http]>=2
Requires-Dist: swh.journal>=2.0
Requires-Dist: swh.model>=7.1.0
Requires-Dist: swh.storage>=2.3.1
Provides-Extra: testing
Requires-Dist: boto3-stubs; extra == "testing"
Requires-Dist: botocore-stubs; extra == "testing"
Requires-Dist: pytest>=8.1; extra == "testing"
Requires-Dist: swh.core[testing]; extra == "testing"
Requires-Dist: swh.journal[pytest]; extra == "testing"
Requires-Dist: types-confluent-kafka; extra == "testing"
Requires-Dist: types-python-dateutil; extra == "testing"
Requires-Dist: types-pyyaml; extra == "testing"
Requires-Dist: types-tqdm; extra == "testing"
Provides-Extra: with-content
Requires-Dist: swh.objstorage; extra == "with-content"
Dynamic: license-file
